{
  "request_id": "TC001",
  "timestamp": "2026-01-15T15:53:13.776758",
  "metrics": [
    {
      "metric_name": "E2E Latency",
      "tier": "stability",
      "value": 0.0,
      "target": 15.0,
      "passed": true,
      "timestamp": "2026-01-15T15:53:13.775680",
      "request_id": "TC001",
      "metadata": {
        "unit": "seconds",
        "start_time": "2026-01-15T15:53:13.775659",
        "end_time": "2026-01-15T15:53:13.775671"
      }
    },
    {
      "metric_name": "JSON Stability Rate",
      "tier": "stability",
      "value": 100.0,
      "target": 99.0,
      "passed": true,
      "timestamp": "2026-01-15T15:53:13.775685",
      "request_id": "TC001",
      "metadata": {
        "total_validations": 3,
        "successful_validations": 3,
        "failed_validations": 0,
        "unit": "percent"
      }
    },
    {
      "metric_name": "Zero-Anachronism Rate",
      "tier": "trust",
      "value": 100.0,
      "target": 100.0,
      "passed": true,
      "timestamp": "2026-01-15T15:53:13.776730",
      "request_id": "TC001",
      "metadata": {
        "total_news": 0,
        "valid_news": 0,
        "invalid_news": 0,
        "note": "No news items to validate"
      }
    },
    {
      "metric_name": "Time-to-Insight Efficiency",
      "tier": "impact",
      "value": 100.0,
      "target": 99.0,
      "passed": true,
      "timestamp": "2026-01-15T15:53:13.776736",
      "request_id": "TC001",
      "metadata": {
        "ai_latency_seconds": 0.0,
        "human_baseline_seconds": 1800,
        "human_baseline_minutes": 30.0,
        "time_saved_seconds": 1800.0,
        "time_saved_minutes": 30.0,
        "unit": "percent"
      }
    },
    {
      "metric_name": "Blind Spot Detection",
      "tier": "impact",
      "value": 0.0,
      "target": 0.4,
      "passed": false,
      "timestamp": "2026-01-15T15:53:13.776749",
      "request_id": "TC001",
      "metadata": {
        "label": "failure",
        "description": "AI가 정답을 찾지 못함",
        "user_belief_similarity": 0.5,
        "ai_conclusion_similarity": 0.5,
        "is_ai_correct": false,
        "is_user_biased": false,
        "user_belief": "시장 전체가 하락해서 같이 떨어진 것 같다. 코스피도 많이 빠졌으니까.",
        "ai_conclusion": "글로벌 시장 변동성 증가",
        "ground_truth": "반도체 수요 둔화에 대한 우려와 경쟁사 대비 실적 전망 하향"
      }
    }
  ],
  "summary": {
    "impact": 50.0,
    "trust": 100.0,
    "stability": 100.0,
    "overall": 80.0
  }
}